{
  "version": "5",
  "dialect": "mysql",
  "id": "7c3e9ab4-e1dd-453d-b62b-0adaae95f06d",
  "prevId": "00000000-0000-0000-0000-000000000000",
  "tables": {
    "categoria": {
      "name": "categoria",
      "columns": {
        "id": {
          "name": "id",
          "type": "int",
          "primaryKey": false,
          "notNull": true,
          "autoincrement": true
        },
        "restaurante_id": {
          "name": "restaurante_id",
          "type": "int",
          "primaryKey": false,
          "notNull": false,
          "autoincrement": false
        },
        "nombre": {
          "name": "nombre",
          "type": "varchar(255)",
          "primaryKey": false,
          "notNull": true,
          "autoincrement": false
        },
        "created_at": {
          "name": "created_at",
          "type": "timestamp",
          "primaryKey": false,
          "notNull": true,
          "autoincrement": false,
          "default": "(now())"
        }
      },
      "indexes": {},
      "foreignKeys": {
        "categoria_restaurante_id_restaurante_id_fk": {
          "name": "categoria_restaurante_id_restaurante_id_fk",
          "tableFrom": "categoria",
          "tableTo": "restaurante",
          "columnsFrom": [
            "restaurante_id"
          ],
          "columnsTo": [
            "id"
          ],
          "onDelete": "no action",
          "onUpdate": "no action"
        }
      },
      "compositePrimaryKeys": {
        "categoria_id": {
          "name": "categoria_id",
          "columns": [
            "id"
          ]
        }
      },
      "uniqueConstraints": {},
      "checkConstraint": {}
    },
    "cliente": {
      "name": "cliente",
      "columns": {
        "id": {
          "name": "id",
          "type": "int",
          "primaryKey": false,
          "notNull": true,
          "autoincrement": true
        },
        "restaurante_id": {
          "name": "restaurante_id",
          "type": "int",
          "primaryKey": false,
          "notNull": true,
          "autoincrement": false
        },
        "nombre": {
          "name": "nombre",
          "type": "varchar(255)",
          "primaryKey": false,
          "notNull": true,
          "autoincrement": false
        },
        "telefono": {
          "name": "telefono",
          "type": "varchar(50)",
          "primaryKey": false,
          "notNull": true,
          "autoincrement": false
        },
        "direccion": {
          "name": "direccion",
          "type": "varchar(255)",
          "primaryKey": false,
          "notNull": false,
          "autoincrement": false
        },
        "puntos": {
          "name": "puntos",
          "type": "int",
          "primaryKey": false,
          "notNull": true,
          "autoincrement": false,
          "default": 0
        },
        "created_at": {
          "name": "created_at",
          "type": "timestamp",
          "primaryKey": false,
          "notNull": true,
          "autoincrement": false,
          "default": "(now())"
        }
      },
      "indexes": {},
      "foreignKeys": {
        "cliente_restaurante_id_restaurante_id_fk": {
          "name": "cliente_restaurante_id_restaurante_id_fk",
          "tableFrom": "cliente",
          "tableTo": "restaurante",
          "columnsFrom": [
            "restaurante_id"
          ],
          "columnsTo": [
            "id"
          ],
          "onDelete": "no action",
          "onUpdate": "no action"
        }
      },
      "compositePrimaryKeys": {
        "cliente_id": {
          "name": "cliente_id",
          "columns": [
            "id"
          ]
        }
      },
      "uniqueConstraints": {},
      "checkConstraint": {}
    },
    "etiqueta": {
      "name": "etiqueta",
      "columns": {
        "id": {
          "name": "id",
          "type": "int",
          "primaryKey": false,
          "notNull": true,
          "autoincrement": true
        },
        "restaurante_id": {
          "name": "restaurante_id",
          "type": "int",
          "primaryKey": false,
          "notNull": true,
          "autoincrement": false
        },
        "producto_id": {
          "name": "producto_id",
          "type": "int",
          "primaryKey": false,
          "notNull": true,
          "autoincrement": false
        },
        "nombre": {
          "name": "nombre",
          "type": "varchar(100)",
          "primaryKey": false,
          "notNull": true,
          "autoincrement": false
        },
        "created_at": {
          "name": "created_at",
          "type": "timestamp",
          "primaryKey": false,
          "notNull": true,
          "autoincrement": false,
          "default": "(now())"
        }
      },
      "indexes": {
        "unique_restaurante_nombre": {
          "name": "unique_restaurante_nombre",
          "columns": [
            "restaurante_id",
            "nombre"
          ],
          "isUnique": true
        }
      },
      "foreignKeys": {
        "etiqueta_restaurante_id_restaurante_id_fk": {
          "name": "etiqueta_restaurante_id_restaurante_id_fk",
          "tableFrom": "etiqueta",
          "tableTo": "restaurante",
          "columnsFrom": [
            "restaurante_id"
          ],
          "columnsTo": [
            "id"
          ],
          "onDelete": "no action",
          "onUpdate": "no action"
        },
        "etiqueta_producto_id_producto_id_fk": {
          "name": "etiqueta_producto_id_producto_id_fk",
          "tableFrom": "etiqueta",
          "tableTo": "producto",
          "columnsFrom": [
            "producto_id"
          ],
          "columnsTo": [
            "id"
          ],
          "onDelete": "no action",
          "onUpdate": "no action"
        }
      },
      "compositePrimaryKeys": {
        "etiqueta_id": {
          "name": "etiqueta_id",
          "columns": [
            "id"
          ]
        }
      },
      "uniqueConstraints": {},
      "checkConstraint": {}
    },
    "ingrediente": {
      "name": "ingrediente",
      "columns": {
        "id": {
          "name": "id",
          "type": "int",
          "primaryKey": false,
          "notNull": true,
          "autoincrement": true
        },
        "restaurante_id": {
          "name": "restaurante_id",
          "type": "int",
          "primaryKey": false,
          "notNull": true,
          "autoincrement": false
        },
        "nombre": {
          "name": "nombre",
          "type": "varchar(255)",
          "primaryKey": false,
          "notNull": true,
          "autoincrement": false
        },
        "created_at": {
          "name": "created_at",
          "type": "timestamp",
          "primaryKey": false,
          "notNull": true,
          "autoincrement": false,
          "default": "(now())"
        }
      },
      "indexes": {},
      "foreignKeys": {
        "ingrediente_restaurante_id_restaurante_id_fk": {
          "name": "ingrediente_restaurante_id_restaurante_id_fk",
          "tableFrom": "ingrediente",
          "tableTo": "restaurante",
          "columnsFrom": [
            "restaurante_id"
          ],
          "columnsTo": [
            "id"
          ],
          "onDelete": "no action",
          "onUpdate": "no action"
        }
      },
      "compositePrimaryKeys": {
        "ingrediente_id": {
          "name": "ingrediente_id",
          "columns": [
            "id"
          ]
        }
      },
      "uniqueConstraints": {},
      "checkConstraint": {}
    },
    "item_pedido": {
      "name": "item_pedido",
      "columns": {
        "id": {
          "name": "id",
          "type": "int",
          "primaryKey": false,
          "notNull": true,
          "autoincrement": true
        },
        "pedido_id": {
          "name": "pedido_id",
          "type": "int",
          "primaryKey": false,
          "notNull": true,
          "autoincrement": false
        },
        "producto_id": {
          "name": "producto_id",
          "type": "int",
          "primaryKey": false,
          "notNull": true,
          "autoincrement": false
        },
        "cliente_nombre": {
          "name": "cliente_nombre",
          "type": "varchar(100)",
          "primaryKey": false,
          "notNull": true,
          "autoincrement": false
        },
        "cantidad": {
          "name": "cantidad",
          "type": "int",
          "primaryKey": false,
          "notNull": false,
          "autoincrement": false,
          "default": 1
        },
        "precio_unitario": {
          "name": "precio_unitario",
          "type": "decimal(10,2)",
          "primaryKey": false,
          "notNull": true,
          "autoincrement": false
        },
        "ingredientes_excluidos": {
          "name": "ingredientes_excluidos",
          "type": "json",
          "primaryKey": false,
          "notNull": false,
          "autoincrement": false
        },
        "estado": {
          "name": "estado",
          "type": "enum('pending','preparing','delivered','served','cancelled')",
          "primaryKey": false,
          "notNull": false,
          "autoincrement": false,
          "default": "'pending'"
        },
        "post_confirmacion": {
          "name": "post_confirmacion",
          "type": "boolean",
          "primaryKey": false,
          "notNull": false,
          "autoincrement": false,
          "default": false
        },
        "created_at": {
          "name": "created_at",
          "type": "timestamp",
          "primaryKey": false,
          "notNull": true,
          "autoincrement": false,
          "default": "(now())"
        }
      },
      "indexes": {},
      "foreignKeys": {},
      "compositePrimaryKeys": {
        "item_pedido_id": {
          "name": "item_pedido_id",
          "columns": [
            "id"
          ]
        }
      },
      "uniqueConstraints": {},
      "checkConstraint": {}
    },
    "item_pedido_delivery": {
      "name": "item_pedido_delivery",
      "columns": {
        "id": {
          "name": "id",
          "type": "int",
          "primaryKey": false,
          "notNull": true,
          "autoincrement": true
        },
        "pedido_delivery_id": {
          "name": "pedido_delivery_id",
          "type": "int",
          "primaryKey": false,
          "notNull": true,
          "autoincrement": false
        },
        "producto_id": {
          "name": "producto_id",
          "type": "int",
          "primaryKey": false,
          "notNull": true,
          "autoincrement": false
        },
        "cantidad": {
          "name": "cantidad",
          "type": "int",
          "primaryKey": false,
          "notNull": false,
          "autoincrement": false,
          "default": 1
        },
        "precio_unitario": {
          "name": "precio_unitario",
          "type": "decimal(10,2)",
          "primaryKey": false,
          "notNull": true,
          "autoincrement": false
        },
        "ingredientes_excluidos": {
          "name": "ingredientes_excluidos",
          "type": "json",
          "primaryKey": false,
          "notNull": false,
          "autoincrement": false
        },
        "es_canje_puntos": {
          "name": "es_canje_puntos",
          "type": "boolean",
          "primaryKey": false,
          "notNull": false,
          "autoincrement": false,
          "default": false
        }
      },
      "indexes": {},
      "foreignKeys": {},
      "compositePrimaryKeys": {
        "item_pedido_delivery_id": {
          "name": "item_pedido_delivery_id",
          "columns": [
            "id"
          ]
        }
      },
      "uniqueConstraints": {},
      "checkConstraint": {}
    },
    "item_pedido_takeaway": {
      "name": "item_pedido_takeaway",
      "columns": {
        "id": {
          "name": "id",
          "type": "int",
          "primaryKey": false,
          "notNull": true,
          "autoincrement": true
        },
        "pedido_takeaway_id": {
          "name": "pedido_takeaway_id",
          "type": "int",
          "primaryKey": false,
          "notNull": true,
          "autoincrement": false
        },
        "producto_id": {
          "name": "producto_id",
          "type": "int",
          "primaryKey": false,
          "notNull": true,
          "autoincrement": false
        },
        "cantidad": {
          "name": "cantidad",
          "type": "int",
          "primaryKey": false,
          "notNull": false,
          "autoincrement": false,
          "default": 1
        },
        "precio_unitario": {
          "name": "precio_unitario",
          "type": "decimal(10,2)",
          "primaryKey": false,
          "notNull": true,
          "autoincrement": false
        },
        "ingredientes_excluidos": {
          "name": "ingredientes_excluidos",
          "type": "json",
          "primaryKey": false,
          "notNull": false,
          "autoincrement": false
        },
        "es_canje_puntos": {
          "name": "es_canje_puntos",
          "type": "boolean",
          "primaryKey": false,
          "notNull": false,
          "autoincrement": false,
          "default": false
        }
      },
      "indexes": {},
      "foreignKeys": {},
      "compositePrimaryKeys": {
        "item_pedido_takeaway_id": {
          "name": "item_pedido_takeaway_id",
          "columns": [
            "id"
          ]
        }
      },
      "uniqueConstraints": {},
      "checkConstraint": {}
    },
    "mesa": {
      "name": "mesa",
      "columns": {
        "id": {
          "name": "id",
          "type": "int",
          "primaryKey": false,
          "notNull": true,
          "autoincrement": true
        },
        "nombre": {
          "name": "nombre",
          "type": "varchar(255)",
          "primaryKey": false,
          "notNull": true,
          "autoincrement": false
        },
        "restaurante_id": {
          "name": "restaurante_id",
          "type": "int",
          "primaryKey": false,
          "notNull": false,
          "autoincrement": false
        },
        "qr_token": {
          "name": "qr_token",
          "type": "varchar(255)",
          "primaryKey": false,
          "notNull": true,
          "autoincrement": false
        },
        "created_at": {
          "name": "created_at",
          "type": "timestamp",
          "primaryKey": false,
          "notNull": true,
          "autoincrement": false,
          "default": "(now())"
        }
      },
      "indexes": {},
      "foreignKeys": {
        "mesa_restaurante_id_restaurante_id_fk": {
          "name": "mesa_restaurante_id_restaurante_id_fk",
          "tableFrom": "mesa",
          "tableTo": "restaurante",
          "columnsFrom": [
            "restaurante_id"
          ],
          "columnsTo": [
            "id"
          ],
          "onDelete": "no action",
          "onUpdate": "no action"
        }
      },
      "compositePrimaryKeys": {
        "mesa_id": {
          "name": "mesa_id",
          "columns": [
            "id"
          ]
        }
      },
      "uniqueConstraints": {
        "mesa_qr_token_unique": {
          "name": "mesa_qr_token_unique",
          "columns": [
            "qr_token"
          ]
        }
      },
      "checkConstraint": {}
    },
    "notificacion": {
      "name": "notificacion",
      "columns": {
        "id": {
          "name": "id",
          "type": "varchar(50)",
          "primaryKey": false,
          "notNull": true,
          "autoincrement": false
        },
        "restaurante_id": {
          "name": "restaurante_id",
          "type": "int",
          "primaryKey": false,
          "notNull": true,
          "autoincrement": false
        },
        "tipo": {
          "name": "tipo",
          "type": "enum('NUEVO_PEDIDO','PEDIDO_CONFIRMADO','PEDIDO_CERRADO','LLAMADA_MOZO','PAGO_RECIBIDO','PRODUCTO_AGREGADO')",
          "primaryKey": false,
          "notNull": true,
          "autoincrement": false
        },
        "mesa_id": {
          "name": "mesa_id",
          "type": "int",
          "primaryKey": false,
          "notNull": false,
          "autoincrement": false
        },
        "mesa_nombre": {
          "name": "mesa_nombre",
          "type": "varchar(255)",
          "primaryKey": false,
          "notNull": false,
          "autoincrement": false
        },
        "pedido_id": {
          "name": "pedido_id",
          "type": "int",
          "primaryKey": false,
          "notNull": false,
          "autoincrement": false
        },
        "mensaje": {
          "name": "mensaje",
          "type": "varchar(500)",
          "primaryKey": false,
          "notNull": true,
          "autoincrement": false
        },
        "detalles": {
          "name": "detalles",
          "type": "varchar(500)",
          "primaryKey": false,
          "notNull": false,
          "autoincrement": false
        },
        "timestamp": {
          "name": "timestamp",
          "type": "timestamp",
          "primaryKey": false,
          "notNull": true,
          "autoincrement": false,
          "default": "(now())"
        },
        "leida": {
          "name": "leida",
          "type": "boolean",
          "primaryKey": false,
          "notNull": true,
          "autoincrement": false,
          "default": false
        }
      },
      "indexes": {},
      "foreignKeys": {
        "notificacion_restaurante_id_restaurante_id_fk": {
          "name": "notificacion_restaurante_id_restaurante_id_fk",
          "tableFrom": "notificacion",
          "tableTo": "restaurante",
          "columnsFrom": [
            "restaurante_id"
          ],
          "columnsTo": [
            "id"
          ],
          "onDelete": "no action",
          "onUpdate": "no action"
        },
        "notificacion_mesa_id_mesa_id_fk": {
          "name": "notificacion_mesa_id_mesa_id_fk",
          "tableFrom": "notificacion",
          "tableTo": "mesa",
          "columnsFrom": [
            "mesa_id"
          ],
          "columnsTo": [
            "id"
          ],
          "onDelete": "no action",
          "onUpdate": "no action"
        }
      },
      "compositePrimaryKeys": {
        "notificacion_id": {
          "name": "notificacion_id",
          "columns": [
            "id"
          ]
        }
      },
      "uniqueConstraints": {},
      "checkConstraint": {}
    },
    "pago": {
      "name": "pago",
      "columns": {
        "id": {
          "name": "id",
          "type": "int",
          "primaryKey": false,
          "notNull": true,
          "autoincrement": true
        },
        "pedido_id": {
          "name": "pedido_id",
          "type": "int",
          "primaryKey": false,
          "notNull": false,
          "autoincrement": false
        },
        "pedido_delivery_id": {
          "name": "pedido_delivery_id",
          "type": "int",
          "primaryKey": false,
          "notNull": false,
          "autoincrement": false
        },
        "pedido_takeaway_id": {
          "name": "pedido_takeaway_id",
          "type": "int",
          "primaryKey": false,
          "notNull": false,
          "autoincrement": false
        },
        "metodo": {
          "name": "metodo",
          "type": "enum('efectivo','mercadopago','transferencia')",
          "primaryKey": false,
          "notNull": true,
          "autoincrement": false
        },
        "estado": {
          "name": "estado",
          "type": "enum('pending','paid','failed')",
          "primaryKey": false,
          "notNull": false,
          "autoincrement": false,
          "default": "'pending'"
        },
        "monto": {
          "name": "monto",
          "type": "decimal(10,2)",
          "primaryKey": false,
          "notNull": true,
          "autoincrement": false
        },
        "mp_payment_id": {
          "name": "mp_payment_id",
          "type": "varchar(255)",
          "primaryKey": false,
          "notNull": false,
          "autoincrement": false
        },
        "created_at": {
          "name": "created_at",
          "type": "timestamp",
          "primaryKey": false,
          "notNull": false,
          "autoincrement": false,
          "default": "(now())"
        }
      },
      "indexes": {},
      "foreignKeys": {},
      "compositePrimaryKeys": {
        "pago_id": {
          "name": "pago_id",
          "columns": [
            "id"
          ]
        }
      },
      "uniqueConstraints": {},
      "checkConstraint": {}
    },
    "pago_subtotal": {
      "name": "pago_subtotal",
      "columns": {
        "id": {
          "name": "id",
          "type": "int",
          "primaryKey": false,
          "notNull": true,
          "autoincrement": true
        },
        "pedido_id": {
          "name": "pedido_id",
          "type": "int",
          "primaryKey": false,
          "notNull": true,
          "autoincrement": false
        },
        "pago_id": {
          "name": "pago_id",
          "type": "int",
          "primaryKey": false,
          "notNull": false,
          "autoincrement": false
        },
        "cliente_nombre": {
          "name": "cliente_nombre",
          "type": "varchar(100)",
          "primaryKey": false,
          "notNull": true,
          "autoincrement": false
        },
        "monto": {
          "name": "monto",
          "type": "decimal(10,2)",
          "primaryKey": false,
          "notNull": true,
          "autoincrement": false
        },
        "estado": {
          "name": "estado",
          "type": "enum('pending','pending_cash','paid','failed')",
          "primaryKey": false,
          "notNull": false,
          "autoincrement": false,
          "default": "'pending'"
        },
        "metodo": {
          "name": "metodo",
          "type": "enum('efectivo','mercadopago','transferencia')",
          "primaryKey": false,
          "notNull": true,
          "autoincrement": false
        },
        "mp_payment_id": {
          "name": "mp_payment_id",
          "type": "varchar(255)",
          "primaryKey": false,
          "notNull": false,
          "autoincrement": false
        },
        "mp_preference_id": {
          "name": "mp_preference_id",
          "type": "varchar(255)",
          "primaryKey": false,
          "notNull": false,
          "autoincrement": false
        },
        "created_at": {
          "name": "created_at",
          "type": "timestamp",
          "primaryKey": false,
          "notNull": false,
          "autoincrement": false,
          "default": "(now())"
        }
      },
      "indexes": {},
      "foreignKeys": {},
      "compositePrimaryKeys": {
        "pago_subtotal_id": {
          "name": "pago_subtotal_id",
          "columns": [
            "id"
          ]
        }
      },
      "uniqueConstraints": {},
      "checkConstraint": {}
    },
    "pedido": {
      "name": "pedido",
      "columns": {
        "id": {
          "name": "id",
          "type": "int",
          "primaryKey": false,
          "notNull": true,
          "autoincrement": true
        },
        "restaurante_id": {
          "name": "restaurante_id",
          "type": "int",
          "primaryKey": false,
          "notNull": false,
          "autoincrement": false
        },
        "mesa_id": {
          "name": "mesa_id",
          "type": "int",
          "primaryKey": false,
          "notNull": false,
          "autoincrement": false
        },
        "nombre_pedido": {
          "name": "nombre_pedido",
          "type": "varchar(255)",
          "primaryKey": false,
          "notNull": false,
          "autoincrement": false
        },
        "estado": {
          "name": "estado",
          "type": "enum('pending','preparing','delivered','served','closed','archived')",
          "primaryKey": false,
          "notNull": false,
          "autoincrement": false,
          "default": "'pending'"
        },
        "total": {
          "name": "total",
          "type": "decimal(10,2)",
          "primaryKey": false,
          "notNull": false,
          "autoincrement": false,
          "default": "'0.00'"
        },
        "pagado": {
          "name": "pagado",
          "type": "boolean",
          "primaryKey": false,
          "notNull": true,
          "autoincrement": false,
          "default": false
        },
        "metodo_pago": {
          "name": "metodo_pago",
          "type": "varchar(50)",
          "primaryKey": false,
          "notNull": false,
          "autoincrement": false
        },
        "created_at": {
          "name": "created_at",
          "type": "timestamp",
          "primaryKey": false,
          "notNull": true,
          "autoincrement": false,
          "default": "(now())"
        },
        "closed_at": {
          "name": "closed_at",
          "type": "timestamp",
          "primaryKey": false,
          "notNull": false,
          "autoincrement": false
        }
      },
      "indexes": {},
      "foreignKeys": {
        "pedido_restaurante_id_restaurante_id_fk": {
          "name": "pedido_restaurante_id_restaurante_id_fk",
          "tableFrom": "pedido",
          "tableTo": "restaurante",
          "columnsFrom": [
            "restaurante_id"
          ],
          "columnsTo": [
            "id"
          ],
          "onDelete": "no action",
          "onUpdate": "no action"
        },
        "pedido_mesa_id_mesa_id_fk": {
          "name": "pedido_mesa_id_mesa_id_fk",
          "tableFrom": "pedido",
          "tableTo": "mesa",
          "columnsFrom": [
            "mesa_id"
          ],
          "columnsTo": [
            "id"
          ],
          "onDelete": "no action",
          "onUpdate": "no action"
        }
      },
      "compositePrimaryKeys": {
        "pedido_id": {
          "name": "pedido_id",
          "columns": [
            "id"
          ]
        }
      },
      "uniqueConstraints": {},
      "checkConstraint": {}
    },
    "pedido_delivery": {
      "name": "pedido_delivery",
      "columns": {
        "id": {
          "name": "id",
          "type": "int",
          "primaryKey": false,
          "notNull": true,
          "autoincrement": true
        },
        "restaurante_id": {
          "name": "restaurante_id",
          "type": "int",
          "primaryKey": false,
          "notNull": false,
          "autoincrement": false
        },
        "cliente_id": {
          "name": "cliente_id",
          "type": "int",
          "primaryKey": false,
          "notNull": false,
          "autoincrement": false
        },
        "direccion": {
          "name": "direccion",
          "type": "varchar(255)",
          "primaryKey": false,
          "notNull": true,
          "autoincrement": false
        },
        "nombre_cliente": {
          "name": "nombre_cliente",
          "type": "varchar(255)",
          "primaryKey": false,
          "notNull": false,
          "autoincrement": false
        },
        "telefono": {
          "name": "telefono",
          "type": "varchar(50)",
          "primaryKey": false,
          "notNull": false,
          "autoincrement": false
        },
        "estado": {
          "name": "estado",
          "type": "enum('pending','preparing','ready','delivered','cancelled','archived')",
          "primaryKey": false,
          "notNull": false,
          "autoincrement": false,
          "default": "'pending'"
        },
        "total": {
          "name": "total",
          "type": "decimal(10,2)",
          "primaryKey": false,
          "notNull": false,
          "autoincrement": false,
          "default": "'0.00'"
        },
        "pagado": {
          "name": "pagado",
          "type": "boolean",
          "primaryKey": false,
          "notNull": true,
          "autoincrement": false,
          "default": false
        },
        "metodo_pago": {
          "name": "metodo_pago",
          "type": "varchar(50)",
          "primaryKey": false,
          "notNull": false,
          "autoincrement": false
        },
        "notas": {
          "name": "notas",
          "type": "varchar(500)",
          "primaryKey": false,
          "notNull": false,
          "autoincrement": false
        },
        "puntos_ganados": {
          "name": "puntos_ganados",
          "type": "int",
          "primaryKey": false,
          "notNull": false,
          "autoincrement": false,
          "default": 0
        },
        "puntos_usados": {
          "name": "puntos_usados",
          "type": "int",
          "primaryKey": false,
          "notNull": false,
          "autoincrement": false,
          "default": 0
        },
        "created_at": {
          "name": "created_at",
          "type": "timestamp",
          "primaryKey": false,
          "notNull": true,
          "autoincrement": false,
          "default": "(now())"
        },
        "delivered_at": {
          "name": "delivered_at",
          "type": "timestamp",
          "primaryKey": false,
          "notNull": false,
          "autoincrement": false
        }
      },
      "indexes": {},
      "foreignKeys": {
        "pedido_delivery_restaurante_id_restaurante_id_fk": {
          "name": "pedido_delivery_restaurante_id_restaurante_id_fk",
          "tableFrom": "pedido_delivery",
          "tableTo": "restaurante",
          "columnsFrom": [
            "restaurante_id"
          ],
          "columnsTo": [
            "id"
          ],
          "onDelete": "no action",
          "onUpdate": "no action"
        },
        "pedido_delivery_cliente_id_cliente_id_fk": {
          "name": "pedido_delivery_cliente_id_cliente_id_fk",
          "tableFrom": "pedido_delivery",
          "tableTo": "cliente",
          "columnsFrom": [
            "cliente_id"
          ],
          "columnsTo": [
            "id"
          ],
          "onDelete": "no action",
          "onUpdate": "no action"
        }
      },
      "compositePrimaryKeys": {
        "pedido_delivery_id": {
          "name": "pedido_delivery_id",
          "columns": [
            "id"
          ]
        }
      },
      "uniqueConstraints": {},
      "checkConstraint": {}
    },
    "pedido_takeaway": {
      "name": "pedido_takeaway",
      "columns": {
        "id": {
          "name": "id",
          "type": "int",
          "primaryKey": false,
          "notNull": true,
          "autoincrement": true
        },
        "restaurante_id": {
          "name": "restaurante_id",
          "type": "int",
          "primaryKey": false,
          "notNull": false,
          "autoincrement": false
        },
        "cliente_id": {
          "name": "cliente_id",
          "type": "int",
          "primaryKey": false,
          "notNull": false,
          "autoincrement": false
        },
        "nombre_cliente": {
          "name": "nombre_cliente",
          "type": "varchar(255)",
          "primaryKey": false,
          "notNull": false,
          "autoincrement": false
        },
        "telefono": {
          "name": "telefono",
          "type": "varchar(50)",
          "primaryKey": false,
          "notNull": false,
          "autoincrement": false
        },
        "estado": {
          "name": "estado",
          "type": "enum('pending','preparing','ready','delivered','cancelled','archived')",
          "primaryKey": false,
          "notNull": false,
          "autoincrement": false,
          "default": "'pending'"
        },
        "total": {
          "name": "total",
          "type": "decimal(10,2)",
          "primaryKey": false,
          "notNull": false,
          "autoincrement": false,
          "default": "'0.00'"
        },
        "pagado": {
          "name": "pagado",
          "type": "boolean",
          "primaryKey": false,
          "notNull": true,
          "autoincrement": false,
          "default": false
        },
        "metodo_pago": {
          "name": "metodo_pago",
          "type": "varchar(50)",
          "primaryKey": false,
          "notNull": false,
          "autoincrement": false
        },
        "notas": {
          "name": "notas",
          "type": "varchar(500)",
          "primaryKey": false,
          "notNull": false,
          "autoincrement": false
        },
        "puntos_ganados": {
          "name": "puntos_ganados",
          "type": "int",
          "primaryKey": false,
          "notNull": false,
          "autoincrement": false,
          "default": 0
        },
        "puntos_usados": {
          "name": "puntos_usados",
          "type": "int",
          "primaryKey": false,
          "notNull": false,
          "autoincrement": false,
          "default": 0
        },
        "created_at": {
          "name": "created_at",
          "type": "timestamp",
          "primaryKey": false,
          "notNull": true,
          "autoincrement": false,
          "default": "(now())"
        },
        "delivered_at": {
          "name": "delivered_at",
          "type": "timestamp",
          "primaryKey": false,
          "notNull": false,
          "autoincrement": false
        }
      },
      "indexes": {},
      "foreignKeys": {
        "pedido_takeaway_restaurante_id_restaurante_id_fk": {
          "name": "pedido_takeaway_restaurante_id_restaurante_id_fk",
          "tableFrom": "pedido_takeaway",
          "tableTo": "restaurante",
          "columnsFrom": [
            "restaurante_id"
          ],
          "columnsTo": [
            "id"
          ],
          "onDelete": "no action",
          "onUpdate": "no action"
        },
        "pedido_takeaway_cliente_id_cliente_id_fk": {
          "name": "pedido_takeaway_cliente_id_cliente_id_fk",
          "tableFrom": "pedido_takeaway",
          "tableTo": "cliente",
          "columnsFrom": [
            "cliente_id"
          ],
          "columnsTo": [
            "id"
          ],
          "onDelete": "no action",
          "onUpdate": "no action"
        }
      },
      "compositePrimaryKeys": {
        "pedido_takeaway_id": {
          "name": "pedido_takeaway_id",
          "columns": [
            "id"
          ]
        }
      },
      "uniqueConstraints": {},
      "checkConstraint": {}
    },
    "producto": {
      "name": "producto",
      "columns": {
        "id": {
          "name": "id",
          "type": "int",
          "primaryKey": false,
          "notNull": true,
          "autoincrement": true
        },
        "restaurante_id": {
          "name": "restaurante_id",
          "type": "int",
          "primaryKey": false,
          "notNull": false,
          "autoincrement": false
        },
        "categoria_id": {
          "name": "categoria_id",
          "type": "int",
          "primaryKey": false,
          "notNull": false,
          "autoincrement": false
        },
        "nombre": {
          "name": "nombre",
          "type": "varchar(255)",
          "primaryKey": false,
          "notNull": true,
          "autoincrement": false
        },
        "descripcion": {
          "name": "descripcion",
          "type": "varchar(255)",
          "primaryKey": false,
          "notNull": false,
          "autoincrement": false
        },
        "precio": {
          "name": "precio",
          "type": "decimal(10,2)",
          "primaryKey": false,
          "notNull": true,
          "autoincrement": false
        },
        "activo": {
          "name": "activo",
          "type": "boolean",
          "primaryKey": false,
          "notNull": false,
          "autoincrement": false,
          "default": true
        },
        "imagen_url": {
          "name": "imagen_url",
          "type": "varchar(255)",
          "primaryKey": false,
          "notNull": false,
          "autoincrement": false
        },
        "created_at": {
          "name": "created_at",
          "type": "timestamp",
          "primaryKey": false,
          "notNull": true,
          "autoincrement": false,
          "default": "(now())"
        }
      },
      "indexes": {},
      "foreignKeys": {
        "producto_restaurante_id_restaurante_id_fk": {
          "name": "producto_restaurante_id_restaurante_id_fk",
          "tableFrom": "producto",
          "tableTo": "restaurante",
          "columnsFrom": [
            "restaurante_id"
          ],
          "columnsTo": [
            "id"
          ],
          "onDelete": "no action",
          "onUpdate": "no action"
        },
        "producto_categoria_id_categoria_id_fk": {
          "name": "producto_categoria_id_categoria_id_fk",
          "tableFrom": "producto",
          "tableTo": "categoria",
          "columnsFrom": [
            "categoria_id"
          ],
          "columnsTo": [
            "id"
          ],
          "onDelete": "no action",
          "onUpdate": "no action"
        }
      },
      "compositePrimaryKeys": {
        "producto_id": {
          "name": "producto_id",
          "columns": [
            "id"
          ]
        }
      },
      "uniqueConstraints": {},
      "checkConstraint": {}
    },
    "producto_ingrediente": {
      "name": "producto_ingrediente",
      "columns": {
        "id": {
          "name": "id",
          "type": "int",
          "primaryKey": false,
          "notNull": true,
          "autoincrement": true
        },
        "producto_id": {
          "name": "producto_id",
          "type": "int",
          "primaryKey": false,
          "notNull": true,
          "autoincrement": false
        },
        "ingrediente_id": {
          "name": "ingrediente_id",
          "type": "int",
          "primaryKey": false,
          "notNull": true,
          "autoincrement": false
        },
        "created_at": {
          "name": "created_at",
          "type": "timestamp",
          "primaryKey": false,
          "notNull": true,
          "autoincrement": false,
          "default": "(now())"
        }
      },
      "indexes": {},
      "foreignKeys": {
        "producto_ingrediente_producto_id_producto_id_fk": {
          "name": "producto_ingrediente_producto_id_producto_id_fk",
          "tableFrom": "producto_ingrediente",
          "tableTo": "producto",
          "columnsFrom": [
            "producto_id"
          ],
          "columnsTo": [
            "id"
          ],
          "onDelete": "no action",
          "onUpdate": "no action"
        },
        "producto_ingrediente_ingrediente_id_ingrediente_id_fk": {
          "name": "producto_ingrediente_ingrediente_id_ingrediente_id_fk",
          "tableFrom": "producto_ingrediente",
          "tableTo": "ingrediente",
          "columnsFrom": [
            "ingrediente_id"
          ],
          "columnsTo": [
            "id"
          ],
          "onDelete": "no action",
          "onUpdate": "no action"
        }
      },
      "compositePrimaryKeys": {
        "producto_ingrediente_id": {
          "name": "producto_ingrediente_id",
          "columns": [
            "id"
          ]
        }
      },
      "uniqueConstraints": {},
      "checkConstraint": {}
    },
    "producto_puntos": {
      "name": "producto_puntos",
      "columns": {
        "id": {
          "name": "id",
          "type": "int",
          "primaryKey": false,
          "notNull": true,
          "autoincrement": true
        },
        "restaurante_id": {
          "name": "restaurante_id",
          "type": "int",
          "primaryKey": false,
          "notNull": true,
          "autoincrement": false
        },
        "producto_id": {
          "name": "producto_id",
          "type": "int",
          "primaryKey": false,
          "notNull": true,
          "autoincrement": false
        },
        "puntos_necesarios": {
          "name": "puntos_necesarios",
          "type": "int",
          "primaryKey": false,
          "notNull": true,
          "autoincrement": false
        },
        "puntos_ganados": {
          "name": "puntos_ganados",
          "type": "int",
          "primaryKey": false,
          "notNull": true,
          "autoincrement": false,
          "default": 0
        }
      },
      "indexes": {},
      "foreignKeys": {
        "producto_puntos_restaurante_id_restaurante_id_fk": {
          "name": "producto_puntos_restaurante_id_restaurante_id_fk",
          "tableFrom": "producto_puntos",
          "tableTo": "restaurante",
          "columnsFrom": [
            "restaurante_id"
          ],
          "columnsTo": [
            "id"
          ],
          "onDelete": "no action",
          "onUpdate": "no action"
        },
        "producto_puntos_producto_id_producto_id_fk": {
          "name": "producto_puntos_producto_id_producto_id_fk",
          "tableFrom": "producto_puntos",
          "tableTo": "producto",
          "columnsFrom": [
            "producto_id"
          ],
          "columnsTo": [
            "id"
          ],
          "onDelete": "no action",
          "onUpdate": "no action"
        }
      },
      "compositePrimaryKeys": {
        "producto_puntos_id": {
          "name": "producto_puntos_id",
          "columns": [
            "id"
          ]
        }
      },
      "uniqueConstraints": {},
      "checkConstraint": {}
    },
    "restaurante": {
      "name": "restaurante",
      "columns": {
        "id": {
          "name": "id",
          "type": "int",
          "primaryKey": false,
          "notNull": true,
          "autoincrement": true
        },
        "email": {
          "name": "email",
          "type": "varchar(255)",
          "primaryKey": false,
          "notNull": true,
          "autoincrement": false
        },
        "nombre": {
          "name": "nombre",
          "type": "varchar(255)",
          "primaryKey": false,
          "notNull": true,
          "autoincrement": false
        },
        "password": {
          "name": "password",
          "type": "varchar(255)",
          "primaryKey": false,
          "notNull": true,
          "autoincrement": false
        },
        "direccion": {
          "name": "direccion",
          "type": "varchar(255)",
          "primaryKey": false,
          "notNull": false,
          "autoincrement": false
        },
        "telefono": {
          "name": "telefono",
          "type": "varchar(255)",
          "primaryKey": false,
          "notNull": false,
          "autoincrement": false
        },
        "imagen_url": {
          "name": "imagen_url",
          "type": "varchar(255)",
          "primaryKey": false,
          "notNull": false,
          "autoincrement": false
        },
        "username": {
          "name": "username",
          "type": "varchar(255)",
          "primaryKey": false,
          "notNull": false,
          "autoincrement": false
        },
        "es_carrito": {
          "name": "es_carrito",
          "type": "boolean",
          "primaryKey": false,
          "notNull": true,
          "autoincrement": false,
          "default": false
        },
        "created_at": {
          "name": "created_at",
          "type": "timestamp",
          "primaryKey": false,
          "notNull": true,
          "autoincrement": false,
          "default": "(now())"
        },
        "mercado_pago_public_key": {
          "name": "mercado_pago_public_key",
          "type": "varchar(255)",
          "primaryKey": false,
          "notNull": false,
          "autoincrement": false
        },
        "mercado_pago_private_key": {
          "name": "mercado_pago_private_key",
          "type": "varchar(255)",
          "primaryKey": false,
          "notNull": false,
          "autoincrement": false
        },
        "mp_access_token": {
          "name": "mp_access_token",
          "type": "varchar(512)",
          "primaryKey": false,
          "notNull": false,
          "autoincrement": false
        },
        "mp_public_key": {
          "name": "mp_public_key",
          "type": "varchar(255)",
          "primaryKey": false,
          "notNull": false,
          "autoincrement": false
        },
        "mp_refresh_token": {
          "name": "mp_refresh_token",
          "type": "varchar(512)",
          "primaryKey": false,
          "notNull": false,
          "autoincrement": false
        },
        "mp_user_id": {
          "name": "mp_user_id",
          "type": "varchar(50)",
          "primaryKey": false,
          "notNull": false,
          "autoincrement": false
        },
        "mp_connected": {
          "name": "mp_connected",
          "type": "boolean",
          "primaryKey": false,
          "notNull": false,
          "autoincrement": false,
          "default": false
        },
        "split_payment": {
          "name": "split_payment",
          "type": "boolean",
          "primaryKey": false,
          "notNull": true,
          "autoincrement": false,
          "default": true
        },
        "item_tracking": {
          "name": "item_tracking",
          "type": "boolean",
          "primaryKey": false,
          "notNull": true,
          "autoincrement": false,
          "default": false
        },
        "solo_carta_digital": {
          "name": "solo_carta_digital",
          "type": "boolean",
          "primaryKey": false,
          "notNull": true,
          "autoincrement": false,
          "default": false
        },
        "delivery_fee": {
          "name": "delivery_fee",
          "type": "decimal(10,2)",
          "primaryKey": false,
          "notNull": true,
          "autoincrement": false,
          "default": "'0.00'"
        },
        "cucuru_customer_id": {
          "name": "cucuru_customer_id",
          "type": "varchar(255)",
          "primaryKey": false,
          "notNull": false,
          "autoincrement": false
        },
        "cucuru_account_number": {
          "name": "cucuru_account_number",
          "type": "varchar(255)",
          "primaryKey": false,
          "notNull": false,
          "autoincrement": false
        },
        "cucuru_alias": {
          "name": "cucuru_alias",
          "type": "varchar(255)",
          "primaryKey": false,
          "notNull": false,
          "autoincrement": false
        },
        "cucuru_enabled": {
          "name": "cucuru_enabled",
          "type": "boolean",
          "primaryKey": false,
          "notNull": true,
          "autoincrement": false,
          "default": false
        },
        "whatsapp_enabled": {
          "name": "whatsapp_enabled",
          "type": "boolean",
          "primaryKey": false,
          "notNull": true,
          "autoincrement": false,
          "default": false
        },
        "whatsapp_number": {
          "name": "whatsapp_number",
          "type": "varchar(50)",
          "primaryKey": false,
          "notNull": false,
          "autoincrement": false
        },
        "transferencia_alias": {
          "name": "transferencia_alias",
          "type": "varchar(255)",
          "primaryKey": false,
          "notNull": false,
          "autoincrement": false
        },
        "sistema_puntos": {
          "name": "sistema_puntos",
          "type": "boolean",
          "primaryKey": false,
          "notNull": true,
          "autoincrement": false,
          "default": false
        }
      },
      "indexes": {},
      "foreignKeys": {},
      "compositePrimaryKeys": {
        "restaurante_id": {
          "name": "restaurante_id",
          "columns": [
            "id"
          ]
        }
      },
      "uniqueConstraints": {
        "restaurante_email_unique": {
          "name": "restaurante_email_unique",
          "columns": [
            "email"
          ]
        },
        "restaurante_username_unique": {
          "name": "restaurante_username_unique",
          "columns": [
            "username"
          ]
        }
      },
      "checkConstraint": {}
    }
  },
  "views": {},
  "_meta": {
    "schemas": {},
    "tables": {},
    "columns": {}
  },
  "internal": {
    "tables": {},
    "indexes": {}
  }
}